{"dogs": [{
			"Name": "satine",
			"Breed": "shepherd",
			"Age": "1.5 years",
			"Owner": "ben",
			"Favorite Food": "cheese sticks",
	},
	{
			"Name": "zeus",
			"Breed": "pittie",
			"Age": "4",
			"Owner": "alicia",
			"Favorite Food": "hot dogs",
		},
		{
			"Name": "beli",
			"Breed": "pit mix",
			"Age": "1",
			"Owner": "liz",
			"Favorite Food": "sausage",
		},
		{
			"Name": "louie",
			"Breed": "farmdog",
			"Age": "6 months",
			"Owner": "celia",
			"Favorite Food": "peanut butter",
			},
			{
				"Name": "madi",
				"Breed": "golden retriever",
				"Age": "9 months",
				"Owner": "austin",
				"Favorite Food": "doggie biscuits",
			},
			{
				"Name": "kiwi",
				"Breed": "half chihuahua half wire-haired terrier",
				"Age": "8ish",
				"Owner": "eileen",
				"Favorite Food": "filet mignon",
			},
			{
				"Name": "bailey",
				"Breed": "mini australian shepherd",
				"Age": "8ish",
				"Owner": "ian",
				"Favorite Food": "french fries",
			}

]



}








{
	"publications": [{
		"Title": "Automatically Generating Cause-and_Effect Questions from Passages",
		"Authors": "Stasaski, K., Rathod, M., Tu, T., Xiao, Y, and Hearst, M.A.",
		"Venue": "BEA Workshop",
		"Year": "2021"
	},
	{
		"Title": "Automatic Feedback Generation for Dialog-Based Language Tutors Using Transformer Models and Active Learning",
		"Authors": "Stasaski, K. and Ramanarayanan, V.",
		"Venue": "Human-in-the-Loop Dialogue Systems Workshop",
		"Year": "2020"
	},
	{
		"Title": "More Diverse Dialogue Datasets via Diversity-Informed Data Collection",
		"Authors": "Stasaski, K., Yang, G., and Hearst, M.A.",
		"Venue": "ACL",
		"Year": "2020"
	},
	{
		"Title": " Construction of a Large Open Access Dialogue Dataset for Tutoring",
		"Authors": "Stasaski, K., Kao, K., and Hearst, M.A.",
		"Venue": "BEA Workshop",
		"Year": "2020"
	},
	{
		"Title": "Multiple Choice Question Generation Utilizing an Ontology",
		"Authors": "Stasaski, K and Hearst, M.A.",
		"Venue": "BEA Workshop",
		"Year": "2017"
	}]

}
